iCEED/__init__.py
iCEED/ec2dofam.py
iCEED/ec2go.py
iCEED/ec2mol.py
iCEED/ec2org.py
iCEED/ec2param.py
iCEED/ec2pdb.py
iCEED/ec2pub.py
iCEED/ec2repath.py
iCEED/ec2seq.py
iCEED/ec2sites.py
iCEED/ec2syn.py
iCEED/Examples/Dom_Fam_examples.py
iCEED/Examples/ECGO_examples.py
iCEED/Examples/Organisms_example.py
iCEED/Examples/PDB_Struct_example.py
iCEED/Examples/PhyCem_Para_examples.py
iCEED/Examples/Pub_Article_example.py
iCEED/Examples/Reaction_Pathway_example.py
iCEED/Examples/Seq_examples.py
iCEED/Examples/Sites_example.py
iCEED/Examples/Small_Mol_examples.py
iCEED/Examples/Synonym_example.py
iCEED-1.1.dist-info/LICENSE.txt
iCEED-1.1.dist-info/METADATA
iCEED-1.1.dist-info/WHEEL
iCEED-1.1.dist-info/top_level.txt
iCEED-1.1.dist-info/RECORD
