Metadata-Version: 2.1
Name: iCEED
Version: 1.1
Summary: Package for customized extraction of enzyme data from bioinformatics databases
Home-page: UNKNOWN
Author: Rajiv Karbhal
Author-email: rajivkarbhal@gmail.com
License: MIT
Platform: UNKNOWN
Classifier: Programming Language :: Python :: 3
Classifier: License :: OSI Approved :: MIT License
Classifier: Operating System :: OS Independent
License-File: LICENSE.txt
Requires-Dist: requests
